culqi_full
