Metadata-Version: 1.2
Name: culqi_full
Version: 1.11
Summary: CULQI
Home-page: https://instagram.com/rockscripts/
Author: @rockscripts
Author-email: rockscripts@gmail.com
License: UNKNOWN
Platform: any
Requires-Python: >=2.7.*
